.gitignore
.travis.yml
LICENSE
README.md
requirements-test.txt
requirements.txt
setup.py
coarij/__init__.py
coarij/cli.py
coarij/ledger.py
coarij/storage.py
coarij.egg-info/PKG-INFO
coarij.egg-info/SOURCES.txt
coarij.egg-info/dependency_links.txt
coarij.egg-info/entry_points.txt
coarij.egg-info/requires.txt
coarij.egg-info/top_level.txt
releases/v1.0.md
tests/__init__.py
tests/test_ledger.py
tests/test_storage.py