Metadata-Version: 2.1
Name: coarij
Version: 0.2.7
Summary: Corpus of Annual Reports in Japan
Home-page: https://github.com/chakki-works/CoARiJ
Author: icoxfog417
Author-email: icoxfog417@yahoo.co.jp
License: MIT
Platform: UNKNOWN
